sweet_pipes/__init__.py
sweet_pipes/coco/__init__.py
sweet_pipes/coco/coco_captions.py
sweet_pipes/coco/coco_detection.py
sweet_pipes/coco/coco_keypoints.py
sweet_pipes/coco/common.py
sweet_pipes/conceptual_captions/__init__.py
sweet_pipes/conceptual_captions/conceptual_captions_12m.py
sweet_pipes/conceptual_captions/conceptual_captions_3m.py
sweet_pipes/laion/__init__.py
sweet_pipes/laion/laion_2b_en.py
sweet_pipes/utils/__init__.py
sweet_pipes/utils/albumentations.py
sweet_pipes/utils/datapipes.py
sweet_pipes/utils/fileio.py
sweet_pipes-0.2.2.dist-info/LICENSE
sweet_pipes-0.2.2.dist-info/METADATA
sweet_pipes-0.2.2.dist-info/WHEEL
sweet_pipes-0.2.2.dist-info/top_level.txt
sweet_pipes-0.2.2.dist-info/RECORD
